elliptic/README.md
elliptic/__init__.py
elliptic/abc.py
elliptic/curves.py
elliptic/fin.py
elliptic/inf.py
elliptic/mod.py
elliptic/poly.py
elliptic/py.typed
elliptic_curves-0.0.4.dist-info/COPYING.md
elliptic_curves-0.0.4.dist-info/METADATA
elliptic_curves-0.0.4.dist-info/WHEEL
elliptic_curves-0.0.4.dist-info/top_level.txt
elliptic_curves-0.0.4.dist-info/RECORD
