Metadata-Version: 2.1
Name: elliptic_curves
Version: 0.0.4
Summary: Implementation of elliptic curves over various fields
Author: Nicolas Canceill
Author-email: nicolas.canceill@gmail.com
License: GPL
Project-URL: Homepage, https://github.com/ncanceill/elliptic_curves
Project-URL: Documentation, https://ncanceill.github.io/elliptic_curves
Classifier: License :: OSI Approved :: GNU General Public License v3 or later (GPLv3+)
Classifier: Operating System :: OS Independent
Classifier: Programming Language :: Python :: 3.11
Requires-Python: >=3.11
License-File: COPYING.md
Provides-Extra: dev
Requires-Dist: setuptools ; extra == 'dev'
Requires-Dist: setuptools-scm ; extra == 'dev'
Provides-Extra: doc
Requires-Dist: pdoc ; extra == 'doc'
Provides-Extra: quality
Requires-Dist: black ; extra == 'quality'
Requires-Dist: flake8 ; extra == 'quality'
Requires-Dist: Flake8-pyproject ; extra == 'quality'
Requires-Dist: isort ; extra == 'quality'
Provides-Extra: testing
Requires-Dist: mypy ; extra == 'testing'
Requires-Dist: types-setuptools ; extra == 'testing'
